djmypypi2/__init__.py
djmypypi2/admin.py
djmypypi2/apps.py
djmypypi2/decorators.py
djmypypi2/factories.py
djmypypi2/models.py
djmypypi2/uids.py
djmypypi2/urls.py
djmypypi2/views.py
djmypypi2/migrations/0001_initial.py
djmypypi2/migrations/0002_version.py
djmypypi2/migrations/0003_token.py
djmypypi2/migrations/0004_alter_version_md5_digest.py
djmypypi2/migrations/__init__.py
djmypypi2/static/css/djmypypi2.css
djmypypi2/static/img/.gitignore
djmypypi2/static/js/djmypypi2.js
djmypypi2/templates/djmypypi2/base.html
djmypypi2/templates/djmypypi2/package-detail.html
djmypypi2/templates/djmypypi2/package-list.html
djmypypi2/test_utils/__init__.py
djmypypi2/test_utils/test_app/__init__.py
djmypypi2/test_utils/test_app/admin.py
djmypypi2/test_utils/test_app/apps.py
djmypypi2/test_utils/test_app/models.py
djmypypi2/test_utils/test_app/migrations/__init__.py
dj_mypypi2-0.2.1.dist-info/METADATA
dj_mypypi2-0.2.1.dist-info/WHEEL
dj_mypypi2-0.2.1.dist-info/licenses/AUTHORS.rst
dj_mypypi2-0.2.1.dist-info/licenses/LICENSE
dj_mypypi2-0.2.1.dist-info/RECORD
