Metadata-Version: 2.4
Name: dj-mypypi2
Version: 0.2.1
Summary: Basic PyPI server for Django projects
Project-URL: Homepage, https://github.com/kverdecia/dj-mypypi2
Project-URL: Repository, https://github.com/kverdecia/dj-mypypi2
Project-URL: Issues, https://github.com/kverdecia/dj-mypypi2/issuess
Author-email: Karel Antonio Verdecia Ortiz <kverdecia@gmail.com>
Maintainer-email: Karel Antonio Verdecia Ortiz <kverdecia@gmail.com>
License-Expression: MIT
License-File: AUTHORS.rst
License-File: LICENSE
Classifier: Development Status :: 5 - Production/Stable
Classifier: Framework :: Django :: 5.0
Classifier: Intended Audience :: Developers
Classifier: Natural Language :: English
Classifier: Programming Language :: Python :: 3.12
Requires-Python: >=3.13
Requires-Dist: cuid>=0.4
Requires-Dist: django>=5.2.3
Requires-Dist: factory-boy>=3.3.3
Requires-Dist: python-dotenv>=1.1.0
Requires-Dist: requests>=2.32.4
Requires-Dist: rich>=14.0.0
